l2hmc/.DS_Store
l2hmc/__about__.py
l2hmc/__init__.py
l2hmc/common.py
l2hmc/configs.py
l2hmc/main.py
l2hmc/train.sh
l2hmc/conf/.DS_Store
l2hmc/conf/__init__.py
l2hmc/conf/config.yaml
l2hmc/conf/annealing_schedule/beta1-4.yaml
l2hmc/conf/annealing_schedule/beta4.yaml
l2hmc/conf/annealing_schedule/constant.yaml
l2hmc/conf/annealing_schedule/default.yaml
l2hmc/conf/conv/default.yaml
l2hmc/conf/conv/none.yaml
l2hmc/conf/dynamics/debug.yaml
l2hmc/conf/dynamics/default.yaml
l2hmc/conf/dynamics/su3.yaml
l2hmc/conf/learning_rate/default.yaml
l2hmc/conf/logdir/debug.yaml
l2hmc/conf/logdir/default.yaml
l2hmc/conf/logdir/test.yaml
l2hmc/conf/loss/default.yaml
l2hmc/conf/mode/cpu.yaml
l2hmc/conf/mode/debug.yaml
l2hmc/conf/mode/default.yaml
l2hmc/conf/mode/exp.yaml
l2hmc/conf/mode/gpu.yaml
l2hmc/conf/mode/test.yaml
l2hmc/conf/net_weights/default.yaml
l2hmc/conf/network/debug.yaml
l2hmc/conf/network/default.yaml
l2hmc/conf/steps/debug.yaml
l2hmc/conf/steps/default.yaml
l2hmc/conf/steps/gpu.yaml
l2hmc/conf/steps/hmc.yaml
l2hmc/conf/steps/long-debug.yaml
l2hmc/conf/sweeps/default.yaml
l2hmc/conf/sweeps/hmc.yaml
l2hmc/distributions/.DS_Store
l2hmc/distributions/__init__.py
l2hmc/distributions/pytorch/__init__.py
l2hmc/distributions/pytorch/haarSUN.py
l2hmc/distributions/tensorflow/__init__.py
l2hmc/distributions/tensorflow/haarSUN.py
l2hmc/dynamics/.DS_Store
l2hmc/dynamics/__init__.py
l2hmc/dynamics/pytorch/__init__.py
l2hmc/dynamics/pytorch/dynamics.py
l2hmc/dynamics/tensorflow/.DS_Store
l2hmc/dynamics/tensorflow/__init__.py
l2hmc/dynamics/tensorflow/dynamics.py
l2hmc/experiment/.DS_Store
l2hmc/experiment/experiment.py
l2hmc/experiment/pytorch/.DS_Store
l2hmc/experiment/pytorch/experiment.py
l2hmc/experiment/tensorflow/.DS_Store
l2hmc/experiment/tensorflow/experiment.py
l2hmc/group/.DS_Store
l2hmc/group/__init__.py
l2hmc/group/generators.py
l2hmc/group/group.py
l2hmc/group/su3/.DS_Store
l2hmc/group/su3/pytorch/__init__.py
l2hmc/group/su3/pytorch/group.py
l2hmc_qcd-0.10.0.dist-info/METADATA
l2hmc_qcd-0.10.0.dist-info/WHEEL
l2hmc_qcd-0.10.0.dist-info/licenses/LICENSE
l2hmc_qcd-0.10.0.dist-info/RECORD
